{
  "db_name": "SQLite",
  "query": "SELECT DISTINCT guild_id FROM jinxxy_user_guild\n            WHERE guild_id NOT IN (SELECT value FROM json_each(?))",
  "describe": {
    "columns": [
      {
        "name": "guild_id",
        "ordinal": 0,
        "type_info": "Integer",
        "origin": {
          "Table": {
            "table": "jinxxy_user_guild",
            "name": "guild_id"
          }
        }
      }
    ],
    "parameters": {
      "Right": 1
    },
    "nullable": [
      false
    ]
  },
  "hash": "95ac497bca735bbe27c833a207fd15d8812ade49b313f1d73a940375baafd964"
}
